odoo/addons/pglogical/README.rst
odoo/addons/pglogical/__init__.py
odoo/addons/pglogical/__manifest__.py
odoo/addons/pglogical/hooks.py
odoo/addons/pglogical/i18n/pglogical.pot
odoo/addons/pglogical/readme/CONFIGURE.rst
odoo/addons/pglogical/readme/CONTRIBUTORS.rst
odoo/addons/pglogical/readme/DESCRIPTION.rst
odoo/addons/pglogical/readme/USAGE.rst
odoo/addons/pglogical/static/description/icon.png
odoo/addons/pglogical/static/description/index.html
odoo/addons/pglogical/tests/__init__.py
odoo/addons/pglogical/tests/test_pglogical.py
odoo12_addon_pglogical-12.0.1.0.1.dist-info/METADATA
odoo12_addon_pglogical-12.0.1.0.1.dist-info/WHEEL
odoo12_addon_pglogical-12.0.1.0.1.dist-info/top_level.txt
odoo12_addon_pglogical-12.0.1.0.1.dist-info/RECORD
