Metadata-Version: 2.1
Name: odoo12-addon-pglogical
Version: 12.0.1.0.1
Summary: Support for replicating Odoo's database
Home-page: https://github.com/OCA/server-backend
Author: Hunki Enterprises BV, Odoo Community Association (OCA)
Author-email: support@odoo-community.org
License: AGPL-3
Platform: UNKNOWN
Classifier: Programming Language :: Python
Classifier: Framework :: Odoo
Classifier: Framework :: Odoo :: 12.0
Classifier: License :: OSI Approved :: GNU Affero General Public License v3
Classifier: Development Status :: 3 - Alpha
Requires-Python: >=3.5
Requires-Dist: odoo (<12.1dev,>=12.0a)
Requires-Dist: sqlparse
